{
  "type": "fulltext-index",
  "name": "galactic-dominion.game_data.planet_search",
  "uuid": "7bb8c9de6236eda0",
  "sourceType": "gocbcore",
  "sourceName": "galactic-dominion",
  "sourceUUID": "0d8be23e952f303532b5b55fb4e08180",
  "planParams": {
    "maxPartitionsPerPIndex": 1024,
    "indexPartitions": 1
  },
  "params": {
    "doc_config": {
      "docid_prefix_delim": "",
      "docid_regexp": "",
      "mode": "scope.collection.type_field",
      "type_field": "type"
    },
    "mapping": {
      "analysis": {},
      "default_analyzer": "standard",
      "default_datetime_parser": "dateTimeOptional",
      "default_field": "_all",
      "default_mapping": {
        "dynamic": false,
        "enabled": false
      },
      "default_type": "_default",
      "docvalues_dynamic": false,
      "index_dynamic": false,
      "store_dynamic": false,
      "type_field": "_type",
      "types": {
        "game_data.planets": {
          "dynamic": false,
          "enabled": true,
          "properties": {
            "description": {
              "dynamic": false,
              "enabled": true,
              "fields": [
                {
                  "analyzer": "en",
                  "docvalues": true,
                  "include_in_all": true,
                  "include_term_vectors": true,
                  "index": true,
                  "name": "description",
                  "store": true,
                  "type": "text"
                }
              ]
            },
            "name": {
              "dynamic": false,
              "enabled": true,
              "fields": [
                {
                  "analyzer": "en",
                  "docvalues": true,
                  "include_in_all": true,
                  "include_term_vectors": true,
                  "index": true,
                  "name": "name",
                  "store": true,
                  "type": "text"
                }
              ]
            }
          }
        }
      }
    },
    "store": {
      "indexType": "scorch",
      "segmentVersion": 15
    }
  },
  "sourceParams": {}
}